paulexyz_pynetbox/__init__.py
paulexyz_pynetbox/core/__init__.py
paulexyz_pynetbox/core/api.py
paulexyz_pynetbox/core/app.py
paulexyz_pynetbox/core/endpoint.py
paulexyz_pynetbox/core/query.py
paulexyz_pynetbox/core/response.py
paulexyz_pynetbox/core/util.py
paulexyz_pynetbox/models/__init__.py
paulexyz_pynetbox/models/circuits.py
paulexyz_pynetbox/models/dcim.py
paulexyz_pynetbox/models/extras.py
paulexyz_pynetbox/models/ipam.py
paulexyz_pynetbox/models/users.py
paulexyz_pynetbox/models/virtualization.py
paulexyz_pynetbox/models/wireless.py
paulexyz_pynetbox-7.0.0.post1.dist-info/LICENSE
paulexyz_pynetbox-7.0.0.post1.dist-info/METADATA
paulexyz_pynetbox-7.0.0.post1.dist-info/WHEEL
paulexyz_pynetbox-7.0.0.post1.dist-info/top_level.txt
paulexyz_pynetbox-7.0.0.post1.dist-info/RECORD
