Metadata-Version: 2.1
Name: paulexyz-pynetbox
Version: 7.0.0.post1
Summary: NetBox API client library
Home-page: UNKNOWN
Author: Zach Moody
Author-email: zmoody@do.co
License: Apache2
Keywords: netbox
Platform: UNKNOWN
Classifier: Intended Audience :: Developers
Classifier: Development Status :: 5 - Production/Stable
Classifier: Programming Language :: Python :: 3
Classifier: Programming Language :: Python :: 3.8
Classifier: Programming Language :: Python :: 3.9
Classifier: Programming Language :: Python :: 3.10
License-File: LICENSE
Requires-Dist: requests (<3.0,>=2.20.0)
